README.rst
setup.cfg
setup.py
DESCtorch/__init__.py
DESCtorch/cluster.py
DESCtorch/dae.py
DESCtorch/dec.py
DESCtorch/desc.py
DESCtorch/network.py
DESCtorch/pytorchtools.py
DESCtorch/sdae.py
DESCtorch/utils.py
DESCtorch.egg-info/PKG-INFO
DESCtorch.egg-info/SOURCES.txt
DESCtorch.egg-info/dependency_links.txt
DESCtorch.egg-info/not-zip-safe
DESCtorch.egg-info/requires.txt
DESCtorch.egg-info/top_level.txt