Metadata-Version: 2.1
Name: DESCtorch
Version: 1.1.0
Summary: Deep Embedded Single-cell RNA-seq Clustering implementation with pytorch
Home-page: https://github.com/yuxiaokang-source/DESCtorch
Author: Xiaokang Yu,Xiangjie Li
Author-email: yuxiaokang2018@163.com,ele717@163.com
License: MIT
Platform: UNKNOWN
Classifier: Development Status :: 3 - Alpha
Classifier: Programming Language :: Python :: 3.6
